{
"Profiles": [
{
  "Working Directory" : "\/Users\/ryan",
  "Prompt Before Closing 2" : 0,
  "Selected Text Color" : {
    "Red Component" : 0,
    "Color Space" : "sRGB",
    "Blue Component" : 0,
    "Alpha Component" : 1,
    "Green Component" : 0
  },
  "Rows" : 25,
  "Ansi 11 Color" : {
    "Red Component" : 0.9259033203125,
    "Color Space" : "sRGB",
    "Blue Component" : 0,
    "Alpha Component" : 1,
    "Green Component" : 0.8833775520324707
  },
  "Use Italic Font" : true,
  "HotKey Characters" : "",
  "Foreground Color" : {
    "Red Component" : 0.86197912693023682,
    "Color Space" : "sRGB",
    "Blue Component" : 0.86198854446411133,
    "Alpha Component" : 1,
    "Green Component" : 0.86199951171875
  },
  "HotKey Window Floats" : true,
  "Use Custom Window Title" : false,
  "Right Option Key Sends" : 0,
  "Show Status Bar" : true,
  "Character Encoding" : 4,
  "Selection Color" : {
    "Red Component" : 0.70196080207824707,
    "Color Space" : "sRGB",
    "Blue Component" : 1,
    "Alpha Component" : 1,
    "Green Component" : 0.84313726425170898
  },
  "Mouse Reporting" : true,
  "Ansi 4 Color" : {
    "Red Component" : 0.15404300391674042,
    "Color Space" : "sRGB",
    "Blue Component" : 0.78216177225112915,
    "Alpha Component" : 1,
    "Green Component" : 0.26474356651306152
  },
  "Non-ASCII Anti Aliased" : true,
  "Sync Title" : false,
  "Disable Window Resizing" : true,
  "Description" : "Default",
  "Close Sessions On End" : 1,
  "Jobs to Ignore" : [
    "rlogin",
    "ssh",
    "slogin",
    "telnet"
  ],
  "Allow Change Cursor Blink" : true,
  "Scrollback Lines" : 0,
  "HotKey Window Reopens On Activation" : false,
  "Draw Powerline Glyphs" : true,
  "Status Bar Layout" : {
    "components" : [
      {
        "class" : "iTermStatusBarCPUUtilizationComponent",
        "configuration" : {
          "knobs" : {
            "base: priority" : 5,
            "shared text color" : {
              "Red Component" : 0.90000000000000002,
              "Color Space" : "sRGB",
              "Blue Component" : 0.63,
              "Alpha Component" : 1,
              "Green Component" : 0.63
            },
            "base: compression resistance" : 1
          },
          "layout advanced configuration dictionary value" : {
            "remove empty components" : true,
            "font" : ".AppleSystemUIFont 12",
            "algorithm" : 0,
            "auto-rainbow style" : 1
          }
        }
      },
      {
        "class" : "iTermStatusBarMemoryUtilizationComponent",
        "configuration" : {
          "knobs" : {
            "base: priority" : 5,
            "shared text color" : {
              "Red Component" : 0.67859999999999998,
              "Color Space" : "sRGB",
              "Blue Component" : 0.63,
              "Alpha Component" : 1,
              "Green Component" : 0.90000000000000002
            },
            "base: compression resistance" : 1
          },
          "layout advanced configuration dictionary value" : {
            "remove empty components" : true,
            "font" : ".AppleSystemUIFont 12",
            "algorithm" : 0,
            "auto-rainbow style" : 1
          }
        }
      },
      {
        "class" : "iTermStatusBarNetworkUtilizationComponent",
        "configuration" : {
          "knobs" : {
            "base: priority" : 5,
            "shared text color" : {
              "Red Component" : 0.63,
              "Color Space" : "sRGB",
              "Blue Component" : 0.90000000000000002,
              "Alpha Component" : 1,
              "Green Component" : 0.72719999999999996
            },
            "base: compression resistance" : 1
          },
          "layout advanced configuration dictionary value" : {
            "remove empty components" : true,
            "font" : ".AppleSystemUIFont 12",
            "algorithm" : 0,
            "auto-rainbow style" : 1
          }
        }
      },
      {
        "class" : "iTermStatusBarSearchFieldComponent",
        "configuration" : {
          "knobs" : {
            "base: priority" : 5,
            "shared text color" : {
              "Red Component" : 0.90000000000000002,
              "Color Space" : "sRGB",
              "Blue Component" : 0.77580000000000005,
              "Alpha Component" : 1,
              "Green Component" : 0.63
            },
            "base: compression resistance" : 1
          },
          "layout advanced configuration dictionary value" : {
            "remove empty components" : true,
            "font" : ".AppleSystemUIFont 12",
            "algorithm" : 0,
            "auto-rainbow style" : 1
          }
        }
      }
    ],
    "advanced configuration" : {
      "remove empty components" : true,
      "font" : ".AppleSystemUIFont 12",
      "algorithm" : 0,
      "auto-rainbow style" : 1
    }
  },
  "Flashing Bell" : false,
  "Cursor Guide Color" : {
    "Red Component" : 0.70213186740875244,
    "Color Space" : "sRGB",
    "Blue Component" : 1,
    "Alpha Component" : 0.25,
    "Green Component" : 0.9268307089805603
  },
  "BM Growl" : false,
  "Ansi 3 Color" : {
    "Red Component" : 0.78058648109436035,
    "Color Space" : "sRGB",
    "Blue Component" : 0,
    "Alpha Component" : 1,
    "Green Component" : 0.76959484815597534
  },
  "Open Password Manager Automatically" : true,
  "Use Non-ASCII Font" : false,
  "Link Color" : {
    "Red Component" : 0.19802422821521759,
    "Color Space" : "sRGB",
    "Blue Component" : 0.9337158203125,
    "Alpha Component" : 1,
    "Green Component" : 0.55789834260940552
  },
  "Shortcut" : "A",
  "Background Image Location" : "",
  "Bold Color" : {
    "Red Component" : 0.99999600648880005,
    "Color Space" : "sRGB",
    "Blue Component" : 1,
    "Alpha Component" : 1,
    "Green Component" : 1
  },
  "Unlimited Scrollback" : true,
  "Custom Command" : "No",
  "HotKey Key Code" : 0,
  "Keyboard Map" : {
    "0xf702-0x240000" : {
      "Text" : "[1;5D",
      "Action" : 10
    },
    "0xf700-0x260000" : {
      "Text" : "[1;6A",
      "Action" : 10
    },
    "0xf704-0x20000" : {
      "Text" : "[1;2P",
      "Action" : 10
    },
    "0x37-0x40000" : {
      "Text" : "0x1f",
      "Action" : 11
    },
    "0x32-0x40000" : {
      "Text" : "0x00",
      "Action" : 11
    },
    "0xf709-0x20000" : {
      "Text" : "[17;2~",
      "Action" : 10
    },
    "0x36-0x3c0000-0x58" : {
      "Version" : 1,
      "Action" : 63,
      "Text" : {
        "guid" : "093E3BB8-7A22-411D-9AFF-EDE954D6AF16"
      },
      "Label" : ""
    },
    "0xf70c-0x20000" : {
      "Text" : "[20;2~",
      "Action" : 10
    },
    "0xf729-0x20000" : {
      "Text" : "[1;2H",
      "Action" : 10
    },
    "0xf72b-0x40000" : {
      "Text" : "[1;5F",
      "Action" : 10
    },
    "0xf705-0x20000" : {
      "Text" : "[1;2Q",
      "Action" : 10
    },
    "0xf703-0x260000" : {
      "Text" : "[1;6C",
      "Action" : 10
    },
    "0xf700-0x220000" : {
      "Text" : "[1;2A",
      "Action" : 10
    },
    "0xf701-0x280000" : {
      "Text" : "0x1b 0x1b 0x5b 0x42",
      "Action" : 11
    },
    "0x33-0x3c0000-0x55" : {
      "Version" : 1,
      "Action" : 63,
      "Text" : {
        "guid" : "EED97A10-9E89-44D4-B56C-C4DB11A6165F"
      },
      "Label" : ""
    },
    "0x33-0x40000" : {
      "Text" : "0x1b",
      "Action" : 11
    },
    "0x39-0x3c0000-0x5c" : {
      "Version" : 1,
      "Action" : 63,
      "Text" : {
        "guid" : "D98BAB0E-E9AC-46A1-A687-54937883F4DA"
      },
      "Label" : ""
    },
    "0x38-0x40000" : {
      "Text" : "0x7f",
      "Action" : 11
    },
    "0xf703-0x220000" : {
      "Text" : "[1;2C",
      "Action" : 10
    },
    "0xf701-0x240000" : {
      "Text" : "[1;5B",
      "Action" : 10
    },
    "0x37-0x3c0000-0x59" : {
      "Version" : 1,
      "Action" : 63,
      "Text" : {
        "guid" : "678927F5-3C5F-4A81-BA22-9CCAB22EE1AB"
      },
      "Label" : ""
    },
    "0xf70d-0x20000" : {
      "Text" : "[21;2~",
      "Action" : 10
    },
    "0xf702-0x260000" : {
      "Text" : "[1;6D",
      "Action" : 10
    },
    "0xf729-0x40000" : {
      "Text" : "[1;5H",
      "Action" : 10
    },
    "0xf706-0x20000" : {
      "Text" : "[1;2R",
      "Action" : 10
    },
    "0x34-0x40000" : {
      "Text" : "0x1c",
      "Action" : 11
    },
    "0xf700-0x280000" : {
      "Text" : "0x1b 0x1b 0x5b 0x41",
      "Action" : 11
    },
    "0x2d-0x40000" : {
      "Text" : "0x1f",
      "Action" : 11
    },
    "0xf70e-0x20000" : {
      "Text" : "[23;2~",
      "Action" : 10
    },
    "0xf702-0x220000" : {
      "Text" : "[1;2D",
      "Action" : 10
    },
    "0x34-0x3c0000-0x56" : {
      "Version" : 1,
      "Action" : 63,
      "Text" : {
        "guid" : "0F581314-5277-4DD5-A9E4-DC9A669C1642"
      },
      "Label" : ""
    },
    "0xf703-0x280000" : {
      "Text" : "0x1b 0x1b 0x5b 0x43",
      "Action" : 11
    },
    "0xf700-0x240000" : {
      "Text" : "[1;5A",
      "Action" : 10
    },
    "0xf707-0x20000" : {
      "Text" : "[1;2S",
      "Action" : 10
    },
    "0xf70a-0x20000" : {
      "Text" : "[18;2~",
      "Action" : 10
    },
    "0x35-0x40000" : {
      "Text" : "0x1d",
      "Action" : 11
    },
    "0x72-0x1c0000-0xf" : {
      "Version" : 1,
      "Action" : 63,
      "Text" : {
        "guid" : "0F581314-5277-4DD5-A9E4-DC9A669C1642"
      },
      "Label" : ""
    },
    "0x31-0x3c0000-0x53" : {
      "Version" : 1,
      "Action" : 63,
      "Text" : {
        "guid" : "C267FD2C-7573-4E36-8175-3D0CE9287AD9"
      },
      "Label" : ""
    },
    "0xf70f-0x20000" : {
      "Text" : "[24;2~",
      "Action" : 10
    },
    "0xf703-0x240000" : {
      "Text" : "[1;5C",
      "Action" : 10
    },
    "0xf701-0x260000" : {
      "Text" : "[1;6B",
      "Action" : 10
    },
    "0x35-0x3c0000-0x57" : {
      "Version" : 1,
      "Action" : 63,
      "Text" : {
        "guid" : "7B5B8A7F-1A8D-4ED2-A505-29EA2FB2FA93"
      },
      "Label" : ""
    },
    "0xf702-0x280000" : {
      "Text" : "0x1b 0x1b 0x5b 0x44",
      "Action" : 11
    },
    "0xf72b-0x20000" : {
      "Text" : "[1;2F",
      "Action" : 10
    },
    "0x36-0x40000" : {
      "Text" : "0x1e",
      "Action" : 11
    },
    "0xf708-0x20000" : {
      "Text" : "[15;2~",
      "Action" : 10
    },
    "0x71-0x1c0000-0xc" : {
      "Version" : 1,
      "Action" : 63,
      "Text" : {
        "guid" : "CD5A0C64-6070-4B8B-B4EC-73492BD65B41"
      },
      "Label" : ""
    },
    "0xf701-0x220000" : {
      "Text" : "[1;2B",
      "Action" : 10
    },
    "0x32-0x3c0000-0x54" : {
      "Version" : 1,
      "Action" : 63,
      "Text" : {
        "guid" : "D01F06F9-872F-4BC2-91B7-7402C0194FD4"
      },
      "Label" : ""
    },
    "0x38-0x3c0000-0x5b" : {
      "Version" : 1,
      "Action" : 63,
      "Text" : {
        "guid" : "C5CA443D-1F55-4402-96EB-F87E7B14E19F"
      },
      "Label" : ""
    },
    "0xf70b-0x20000" : {
      "Text" : "[19;2~",
      "Action" : 10
    }
  },
  "Ansi 14 Color" : {
    "Red Component" : 0.37597531080245972,
    "Color Space" : "sRGB",
    "Blue Component" : 1,
    "Alpha Component" : 1,
    "Green Component" : 0.99263292551040649
  },
  "Ansi 2 Color" : {
    "Red Component" : 0,
    "Color Space" : "sRGB",
    "Blue Component" : 0,
    "Alpha Component" : 1,
    "Green Component" : 0.7607843279838562
  },
  "Send Code When Idle" : false,
  "ASCII Anti Aliased" : true,
  "Tags" : [

  ],
  "Ansi 9 Color" : {
    "Red Component" : 0.8659515380859375,
    "Color Space" : "sRGB",
    "Blue Component" : 0.45833224058151245,
    "Alpha Component" : 1,
    "Green Component" : 0.47524076700210571
  },
  "Use Bold Font" : true,
  "Silence Bell" : true,
  "Ansi 12 Color" : {
    "Red Component" : 0.65349078178405762,
    "Color Space" : "sRGB",
    "Blue Component" : 0.9485321044921875,
    "Alpha Component" : 1,
    "Green Component" : 0.67044717073440552
  },
  "Window Type" : 0,
  "Allow Title Reporting" : true,
  "Use Bright Bold" : true,
  "Send Bell Alert" : false,
  "HotKey Modifier Activation" : 0,
  "Cursor Text Color" : {
    "Red Component" : 0,
    "Color Space" : "sRGB",
    "Blue Component" : 0,
    "Alpha Component" : 1,
    "Green Component" : 0
  },
  "HotKey Window Dock Click Action" : 0,
  "Default Bookmark" : "No",
  "Cursor Color" : {
    "Red Component" : 0.99997633695602417,
    "Color Space" : "sRGB",
    "Blue Component" : 0.99998724460601807,
    "Alpha Component" : 1,
    "Green Component" : 1
  },
  "Ansi 1 Color" : {
    "Red Component" : 0.7074432373046875,
    "Color Space" : "sRGB",
    "Blue Component" : 0.16300037503242493,
    "Alpha Component" : 1,
    "Green Component" : 0.23660069704055786
  },
  "Name" : "Default",
  "Blinking Cursor" : true,
  "Send Terminal Generated Alerts" : false,
  "Has Hotkey" : false,
  "Guid" : "2651816F-2E96-4D73-AC2C-0924B67FAC1D",
  "Ansi 8 Color" : {
    "Red Component" : 0.40781760215759277,
    "Color Space" : "sRGB",
    "Blue Component" : 0.4078223705291748,
    "Alpha Component" : 1,
    "Green Component" : 0.40782788395881653
  },
  "Ansi 10 Color" : {
    "Red Component" : 0.3450070321559906,
    "Color Space" : "sRGB",
    "Blue Component" : 0.56541937589645386,
    "Alpha Component" : 1,
    "Green Component" : 0.9042816162109375
  },
  "Idle Code" : 0,
  "Badge Color" : {
    "Red Component" : 1,
    "Color Space" : "sRGB",
    "Blue Component" : 1,
    "Alpha Component" : 0.5,
    "Green Component" : 1
  },
  "Ambiguous Double Width" : false,
  "Blur Radius" : 7.0347156930477066,
  "Cursor Type" : 2,
  "Ansi 0 Color" : {
    "Red Component" : 0.078431375324726105,
    "Color Space" : "sRGB",
    "Blue Component" : 0.11764705926179886,
    "Alpha Component" : 1,
    "Green Component" : 0.098039217293262482
  },
  "Blur" : false,
  "Normal Font" : "FiraCodeNerdFontCompleteM-Regular 18",
  "Vertical Spacing" : 1,
  "Disable Printing" : true,
  "Ansi 7 Color" : {
    "Red Component" : 0.7810397744178772,
    "Color Space" : "sRGB",
    "Blue Component" : 0.78104829788208008,
    "Alpha Component" : 1,
    "Green Component" : 0.78105825185775757
  },
  "Place Prompt at First Column" : false,
  "HotKey Window AutoHides" : true,
  "Command" : "",
  "Terminal Type" : "xterm-256color",
  "Horizontal Spacing" : 1,
  "Option Key Sends" : 0,
  "Only The Default BG Color Uses Transparency" : false,
  "HotKey Window Animates" : true,
  "HotKey Modifier Flags" : 0,
  "Ansi 15 Color" : {
    "Red Component" : 0.99999600648880005,
    "Color Space" : "sRGB",
    "Blue Component" : 1,
    "Alpha Component" : 1,
    "Green Component" : 1
  },
  "Open Toolbelt" : false,
  "Ansi 6 Color" : {
    "Red Component" : 0,
    "Color Space" : "sRGB",
    "Blue Component" : 0.78166204690933228,
    "Alpha Component" : 1,
    "Green Component" : 0.77425903081893921
  },
  "Transparency" : 0,
  "HotKey Activated By Modifier" : false,
  "Background Color" : {
    "Red Component" : 0.0806884765625,
    "Color Space" : "sRGB",
    "Blue Component" : 0.12103271484375,
    "Alpha Component" : 1,
    "Green Component" : 0.099111050367355347
  },
  "Screen" : -1,
  "HotKey Characters Ignoring Modifiers" : "",
  "Send Session Ended Alert" : false,
  "Non Ascii Font" : "Monaco 12",
  "Ansi 13 Color" : {
    "Red Component" : 0.8821563720703125,
    "Color Space" : "sRGB",
    "Blue Component" : 0.8821563720703125,
    "Alpha Component" : 1,
    "Green Component" : 0.4927266538143158
  },
  "Columns" : 80,
  "HotKey Alternate Shortcuts" : [

  ],
  "Visual Bell" : false,
  "Custom Directory" : "Recycle",
  "ASCII Ligatures" : false,
  "Ansi 5 Color" : {
    "Red Component" : 0.752197265625,
    "Color Space" : "sRGB",
    "Blue Component" : 0.74494361877441406,
    "Alpha Component" : 1,
    "Green Component" : 0.24931684136390686
  }
},
{
  "Set Local Environment Vars" : true,
  "Working Directory" : "\/Users\/ryan",
  "Prompt Before Closing 2" : 0,
  "Selected Text Color" : {
    "Red Component" : 0,
    "Color Space" : "sRGB",
    "Blue Component" : 0,
    "Alpha Component" : 1,
    "Green Component" : 0
  },
  "Rows" : 50,
  "Ansi 11 Color" : {
    "Red Component" : 0.9259033203125,
    "Color Space" : "sRGB",
    "Blue Component" : 0,
    "Alpha Component" : 1,
    "Green Component" : 0.8833775520324707
  },
  "Use Italic Font" : true,
  "HotKey Characters" : " ",
  "Foreground Color" : {
    "Red Component" : 0.86197912693023682,
    "Color Space" : "sRGB",
    "Blue Component" : 0.86198854446411133,
    "Alpha Component" : 1,
    "Green Component" : 0.86199951171875
  },
  "HotKey Window Floats" : true,
  "Use Custom Window Title" : false,
  "Right Option Key Sends" : 0,
  "Show Status Bar" : true,
  "Character Encoding" : 4,
  "Selection Color" : {
    "Red Component" : 0.70196080207824707,
    "Color Space" : "sRGB",
    "Blue Component" : 1,
    "Alpha Component" : 1,
    "Green Component" : 0.84313726425170898
  },
  "Mouse Reporting" : true,
  "Ansi 4 Color" : {
    "Red Component" : 0.15404300391674042,
    "Color Space" : "sRGB",
    "Blue Component" : 0.78216177225112915,
    "Alpha Component" : 1,
    "Green Component" : 0.26474356651306152
  },
  "Non-ASCII Anti Aliased" : true,
  "Sync Title" : false,
  "Disable Window Resizing" : true,
  "Description" : "Default",
  "Close Sessions On End" : 1,
  "Jobs to Ignore" : [
    "rlogin",
    "ssh",
    "slogin",
    "telnet"
  ],
  "Allow Change Cursor Blink" : true,
  "Scrollback Lines" : 0,
  "HotKey Window Reopens On Activation" : false,
  "Draw Powerline Glyphs" : true,
  "Status Bar Layout" : {
    "components" : [
      {
        "class" : "iTermStatusBarCPUUtilizationComponent",
        "configuration" : {
          "knobs" : {
            "base: priority" : 5,
            "base: compression resistance" : 1,
            "shared text color" : {
              "Red Component" : 0.86000317335128784,
              "Color Space" : "P3",
              "Blue Component" : 0.63590967655181885,
              "Alpha Component" : 1,
              "Green Component" : 0.64143353700637817
            }
          },
          "layout advanced configuration dictionary value" : {
            "remove empty components" : true,
            "font" : ".AppleSystemUIFont 12",
            "algorithm" : 0,
            "auto-rainbow style" : 1
          }
        }
      },
      {
        "class" : "iTermStatusBarMemoryUtilizationComponent",
        "configuration" : {
          "knobs" : {
            "base: priority" : 5,
            "base: compression resistance" : 1,
            "shared text color" : {
              "Red Component" : 0.68831604719161987,
              "Color Space" : "P3",
              "Blue Component" : 0.82982367277145386,
              "Alpha Component" : 1,
              "Green Component" : 0.89269793033599854
            }
          },
          "layout advanced configuration dictionary value" : {
            "remove empty components" : true,
            "font" : ".AppleSystemUIFont 12",
            "algorithm" : 0,
            "auto-rainbow style" : 1
          }
        }
      },
      {
        "class" : "iTermStatusBarNetworkUtilizationComponent",
        "configuration" : {
          "knobs" : {
            "base: priority" : 5,
            "base: compression resistance" : 1,
            "shared text color" : {
              "Red Component" : 0.86000508069992065,
              "Color Space" : "P3",
              "Blue Component" : 0.76881879568099976,
              "Alpha Component" : 1,
              "Green Component" : 0.6414305567741394
            }
          },
          "layout advanced configuration dictionary value" : {
            "remove empty components" : true,
            "font" : ".AppleSystemUIFont 12",
            "algorithm" : 0,
            "auto-rainbow style" : 1
          }
        }
      }
    ],
    "advanced configuration" : {
      "remove empty components" : true,
      "font" : ".AppleSystemUIFont 12",
      "algorithm" : 0,
      "auto-rainbow style" : 1
    }
  },
  "Cursor Shadow" : true,
  "Flashing Bell" : false,
  "Cursor Guide Color" : {
    "Red Component" : 0.70213186740875244,
    "Color Space" : "sRGB",
    "Blue Component" : 1,
    "Alpha Component" : 0.25,
    "Green Component" : 0.9268307089805603
  },
  "BM Growl" : false,
  "Ansi 3 Color" : {
    "Red Component" : 0.78058648109436035,
    "Color Space" : "sRGB",
    "Blue Component" : 0,
    "Alpha Component" : 1,
    "Green Component" : 0.76959484815597534
  },
  "Open Password Manager Automatically" : true,
  "Icon" : 1,
  "Link Color" : {
    "Red Component" : 0.19802422821521759,
    "Color Space" : "sRGB",
    "Blue Component" : 0.9337158203125,
    "Alpha Component" : 1,
    "Green Component" : 0.55789834260940552
  },
  "Shortcut" : "",
  "Use Non-ASCII Font" : false,
  "Background Image Location" : "",
  "Bold Color" : {
    "Red Component" : 0.99999600648880005,
    "Color Space" : "sRGB",
    "Blue Component" : 1,
    "Alpha Component" : 1,
    "Green Component" : 1
  },
  "Unlimited Scrollback" : true,
  "Custom Command" : "No",
  "HotKey Key Code" : 49,
  "Keyboard Map" : {
    "0xf702-0x240000" : {
      "Text" : "[1;5D",
      "Action" : 10
    },
    "0xf700-0x260000" : {
      "Text" : "[1;6A",
      "Action" : 10
    },
    "0xf704-0x20000" : {
      "Text" : "[1;2P",
      "Action" : 10
    },
    "0x37-0x40000" : {
      "Text" : "0x1f",
      "Action" : 11
    },
    "0x32-0x40000" : {
      "Text" : "0x00",
      "Action" : 11
    },
    "0xf709-0x20000" : {
      "Text" : "[17;2~",
      "Action" : 10
    },
    "0x36-0x3c0000-0x58" : {
      "Version" : 1,
      "Action" : 63,
      "Text" : {
        "guid" : "093E3BB8-7A22-411D-9AFF-EDE954D6AF16"
      },
      "Label" : ""
    },
    "0xf70c-0x20000" : {
      "Text" : "[20;2~",
      "Action" : 10
    },
    "0xf729-0x20000" : {
      "Text" : "[1;2H",
      "Action" : 10
    },
    "0xf72b-0x40000" : {
      "Text" : "[1;5F",
      "Action" : 10
    },
    "0xf705-0x20000" : {
      "Text" : "[1;2Q",
      "Action" : 10
    },
    "0xf703-0x260000" : {
      "Text" : "[1;6C",
      "Action" : 10
    },
    "0xf700-0x220000" : {
      "Text" : "[1;2A",
      "Action" : 10
    },
    "0xf701-0x280000" : {
      "Text" : "0x1b 0x1b 0x5b 0x42",
      "Action" : 11
    },
    "0x33-0x3c0000-0x55" : {
      "Version" : 1,
      "Action" : 63,
      "Text" : {
        "guid" : "EED97A10-9E89-44D4-B56C-C4DB11A6165F"
      },
      "Label" : ""
    },
    "0x33-0x40000" : {
      "Text" : "0x1b",
      "Action" : 11
    },
    "0x39-0x3c0000-0x5c" : {
      "Version" : 1,
      "Action" : 63,
      "Text" : {
        "guid" : "D98BAB0E-E9AC-46A1-A687-54937883F4DA"
      },
      "Label" : ""
    },
    "0x38-0x40000" : {
      "Text" : "0x7f",
      "Action" : 11
    },
    "0xf703-0x220000" : {
      "Text" : "[1;2C",
      "Action" : 10
    },
    "0xf701-0x240000" : {
      "Text" : "[1;5B",
      "Action" : 10
    },
    "0x37-0x3c0000-0x59" : {
      "Version" : 1,
      "Action" : 63,
      "Text" : {
        "guid" : "678927F5-3C5F-4A81-BA22-9CCAB22EE1AB"
      },
      "Label" : ""
    },
    "0xf70d-0x20000" : {
      "Text" : "[21;2~",
      "Action" : 10
    },
    "0xf702-0x260000" : {
      "Text" : "[1;6D",
      "Action" : 10
    },
    "0xf729-0x40000" : {
      "Text" : "[1;5H",
      "Action" : 10
    },
    "0xf706-0x20000" : {
      "Text" : "[1;2R",
      "Action" : 10
    },
    "0x34-0x40000" : {
      "Text" : "0x1c",
      "Action" : 11
    },
    "0xf700-0x280000" : {
      "Text" : "0x1b 0x1b 0x5b 0x41",
      "Action" : 11
    },
    "0x2d-0x40000" : {
      "Text" : "0x1f",
      "Action" : 11
    },
    "0xf70e-0x20000" : {
      "Text" : "[23;2~",
      "Action" : 10
    },
    "0xf702-0x220000" : {
      "Text" : "[1;2D",
      "Action" : 10
    },
    "0x34-0x3c0000-0x56" : {
      "Version" : 1,
      "Action" : 63,
      "Text" : {
        "guid" : "0F581314-5277-4DD5-A9E4-DC9A669C1642"
      },
      "Label" : ""
    },
    "0xf703-0x280000" : {
      "Text" : "0x1b 0x1b 0x5b 0x43",
      "Action" : 11
    },
    "0xf700-0x240000" : {
      "Text" : "[1;5A",
      "Action" : 10
    },
    "0xf707-0x20000" : {
      "Text" : "[1;2S",
      "Action" : 10
    },
    "0xf70a-0x20000" : {
      "Text" : "[18;2~",
      "Action" : 10
    },
    "0x35-0x40000" : {
      "Text" : "0x1d",
      "Action" : 11
    },
    "0x72-0x1c0000-0xf" : {
      "Version" : 1,
      "Action" : 63,
      "Text" : {
        "guid" : "0F581314-5277-4DD5-A9E4-DC9A669C1642"
      },
      "Label" : ""
    },
    "0x31-0x3c0000-0x53" : {
      "Version" : 1,
      "Action" : 63,
      "Text" : {
        "guid" : "C267FD2C-7573-4E36-8175-3D0CE9287AD9"
      },
      "Label" : ""
    },
    "0xf70f-0x20000" : {
      "Text" : "[24;2~",
      "Action" : 10
    },
    "0xf703-0x240000" : {
      "Text" : "[1;5C",
      "Action" : 10
    },
    "0xf701-0x260000" : {
      "Text" : "[1;6B",
      "Action" : 10
    },
    "0x35-0x3c0000-0x57" : {
      "Version" : 1,
      "Action" : 63,
      "Text" : {
        "guid" : "7B5B8A7F-1A8D-4ED2-A505-29EA2FB2FA93"
      },
      "Label" : ""
    },
    "0xf702-0x280000" : {
      "Text" : "0x1b 0x1b 0x5b 0x44",
      "Action" : 11
    },
    "0xf72b-0x20000" : {
      "Text" : "[1;2F",
      "Action" : 10
    },
    "0x36-0x40000" : {
      "Text" : "0x1e",
      "Action" : 11
    },
    "0xf708-0x20000" : {
      "Text" : "[15;2~",
      "Action" : 10
    },
    "0xf701-0x220000" : {
      "Text" : "[1;2B",
      "Action" : 10
    },
    "0xf70b-0x20000" : {
      "Text" : "[19;2~",
      "Action" : 10
    },
    "0x32-0x3c0000-0x54" : {
      "Version" : 1,
      "Action" : 63,
      "Text" : {
        "guid" : "D01F06F9-872F-4BC2-91B7-7402C0194FD4"
      },
      "Label" : ""
    },
    "0x38-0x3c0000-0x5b" : {
      "Version" : 1,
      "Action" : 63,
      "Text" : {
        "guid" : "C5CA443D-1F55-4402-96EB-F87E7B14E19F"
      },
      "Label" : ""
    },
    "0x71-0x1c0000-0xc" : {
      "Version" : 1,
      "Action" : 63,
      "Text" : {
        "guid" : "CD5A0C64-6070-4B8B-B4EC-73492BD65B41"
      },
      "Label" : ""
    }
  },
  "Ansi 14 Color" : {
    "Red Component" : 0.37597531080245972,
    "Color Space" : "sRGB",
    "Blue Component" : 1,
    "Alpha Component" : 1,
    "Green Component" : 0.99263292551040649
  },
  "Ansi 2 Color" : {
    "Red Component" : 0,
    "Color Space" : "sRGB",
    "Blue Component" : 0,
    "Alpha Component" : 1,
    "Green Component" : 0.7607843279838562
  },
  "Send Code When Idle" : false,
  "ASCII Anti Aliased" : true,
  "Tags" : [

  ],
  "Ansi 9 Color" : {
    "Red Component" : 0.8659515380859375,
    "Color Space" : "sRGB",
    "Blue Component" : 0.45833224058151245,
    "Alpha Component" : 1,
    "Green Component" : 0.47524076700210571
  },
  "Use Bold Font" : true,
  "Silence Bell" : true,
  "Ansi 12 Color" : {
    "Red Component" : 0.65349078178405762,
    "Color Space" : "sRGB",
    "Blue Component" : 0.9485321044921875,
    "Alpha Component" : 1,
    "Green Component" : 0.67044717073440552
  },
  "Window Type" : 2,
  "Allow Title Reporting" : true,
  "Use Bright Bold" : true,
  "Send Bell Alert" : false,
  "HotKey Modifier Activation" : 0,
  "Cursor Text Color" : {
    "Red Component" : 0,
    "Color Space" : "sRGB",
    "Blue Component" : 0,
    "Alpha Component" : 1,
    "Green Component" : 0
  },
  "HotKey Window Dock Click Action" : 2,
  "Ansi 1 Color" : {
    "Red Component" : 0.7074432373046875,
    "Color Space" : "sRGB",
    "Blue Component" : 0.16300037503242493,
    "Alpha Component" : 1,
    "Green Component" : 0.23660069704055786
  },
  "Default Bookmark" : "No",
  "Disable Smcup Rmcup" : true,
  "Name" : "Sticky Term",
  "Blinking Cursor" : true,
  "Send Terminal Generated Alerts" : false,
  "Cursor Color" : {
    "Red Component" : 0.99997633695602417,
    "Color Space" : "sRGB",
    "Blue Component" : 0.99998724460601807,
    "Alpha Component" : 1,
    "Green Component" : 1
  },
  "Guid" : "61DC03AF-741F-4AFB-9F0D-38292BAFC237",
  "Has Hotkey" : true,
  "Ansi 8 Color" : {
    "Red Component" : 0.40781760215759277,
    "Color Space" : "sRGB",
    "Blue Component" : 0.4078223705291748,
    "Alpha Component" : 1,
    "Green Component" : 0.40782788395881653
  },
  "Ansi 10 Color" : {
    "Red Component" : 0.3450070321559906,
    "Color Space" : "sRGB",
    "Blue Component" : 0.56541937589645386,
    "Alpha Component" : 1,
    "Green Component" : 0.9042816162109375
  },
  "Idle Code" : 0,
  "Badge Color" : {
    "Red Component" : 1,
    "Color Space" : "sRGB",
    "Blue Component" : 1,
    "Alpha Component" : 0.5,
    "Green Component" : 1
  },
  "Semantic History" : {
    "text" : "",
    "action" : "best editor",
    "editor" : "com.github.atom"
  },
  "Ambiguous Double Width" : false,
  "Blur Radius" : 13.487238977310504,
  "Cursor Type" : 2,
  "Ansi 0 Color" : {
    "Red Component" : 0.078431375324726105,
    "Color Space" : "sRGB",
    "Blue Component" : 0.11764705926179886,
    "Alpha Component" : 1,
    "Green Component" : 0.098039217293262482
  },
  "Blur" : true,
  "Normal Font" : "FiraCodeNerdFontCompleteM-Regular 18",
  "Vertical Spacing" : 1,
  "Disable Printing" : true,
  "Ansi 7 Color" : {
    "Red Component" : 0.7810397744178772,
    "Color Space" : "sRGB",
    "Blue Component" : 0.78104829788208008,
    "Alpha Component" : 1,
    "Green Component" : 0.78105825185775757
  },
  "Place Prompt at First Column" : false,
  "Space" : -1,
  "HotKey Window AutoHides" : true,
  "Command" : "",
  "Terminal Type" : "xterm-256color",
  "Horizontal Spacing" : 1,
  "Option Key Sends" : 0,
  "Only The Default BG Color Uses Transparency" : true,
  "HotKey Window Animates" : true,
  "HotKey Modifier Flags" : 1572864,
  "Ansi 15 Color" : {
    "Red Component" : 0.99999600648880005,
    "Color Space" : "sRGB",
    "Blue Component" : 1,
    "Alpha Component" : 1,
    "Green Component" : 1
  },
  "Open Toolbelt" : false,
  "Minimum Contrast" : 0,
  "Ansi 6 Color" : {
    "Red Component" : 0,
    "Color Space" : "sRGB",
    "Blue Component" : 0.78166204690933228,
    "Alpha Component" : 1,
    "Green Component" : 0.77425903081893921
  },
  "Transparency" : 0.040320603390957485,
  "HotKey Activated By Modifier" : false,
  "Background Color" : {
    "Red Component" : 0.0806884765625,
    "Color Space" : "sRGB",
    "Blue Component" : 0.12103271484375,
    "Alpha Component" : 1,
    "Green Component" : 0.099111050367355347
  },
  "Screen" : -2,
  "HotKey Characters Ignoring Modifiers" : " ",
  "Initial Use Transparency" : false,
  "Bound Hosts" : [

  ],
  "Send Session Ended Alert" : false,
  "Non Ascii Font" : "Monaco 12",
  "Ansi 13 Color" : {
    "Red Component" : 0.8821563720703125,
    "Color Space" : "sRGB",
    "Blue Component" : 0.8821563720703125,
    "Alpha Component" : 1,
    "Green Component" : 0.4927266538143158
  },
  "Columns" : 80,
  "HotKey Alternate Shortcuts" : [

  ],
  "Unicode Normalization" : 0,
  "Visual Bell" : false,
  "ASCII Ligatures" : false,
  "Ansi 5 Color" : {
    "Red Component" : 0.752197265625,
    "Color Space" : "sRGB",
    "Blue Component" : 0.74494361877441406,
    "Alpha Component" : 1,
    "Green Component" : 0.24931684136390686
  },
  "Custom Directory" : "Recycle"
}
]
}
